cpu_controller/alu.v
module alu (
    input [3:0] a, b,
    input [1:0] sel,
    output reg [3:0] out,
    output reg carry_out,
    output reg zero_flag   // Make zero_flag reg
);

    always @(*) begin
        case (sel)
            2'b00: {carry_out, out} = {1'b0, a & b}; // AND
            2'b01: {carry_out, out} = {1'b0, a | b}; // OR
            2'b10: {carry_out, out} = {1'b0, a ^ b}; // XOR
            2'b11: {carry_out, out} = a + b;         // ADD
            default: {carry_out, out} = 5'b0;
        endcase

        // Zero flag calculation inside the always block
        if (out == 4'b0000)
            zero_flag = 1'b1;
        else
            zero_flag = 1'b0;
    end

endmodule

cpu_controller/register.v
module register (
    input [3:0] d,
    input clk, load, rstn,
    output reg [3:0] q
);

    initial begin
        q = 4'b0000;
    end

    always @(posedge clk or negedge rstn) begin
        if (!rstn)
            q <= 4'b0000;      // Reset takes highest priority
        else if (load)
            q <= d;            // Load when load=1
    end

endmodule

cpu_controller/mux.v
module mux (
    input [3:0] a, b,
    input sel,
    output [3:0] out
);

assign out = (sel) ? b : a;

endmodule

cpu_controller/rom.v
// module rom (
//     input [2:0] addr,
//     output reg [3:0] out
// );

//     always @(*) begin
//         case (addr)
//             3'b000: out = 4'b0001; // AND   alu_sel=00, mux_sel=0, load=1
//             3'b001: out = 4'b0101; // OR    alu_sel=01, mux_sel=0, load=1
//             3'b010: out = 4'b1001; // XOR   alu_sel=10, mux_sel=0, load=1
//             3'b011: out = 4'b1101; // ADD   alu_sel=11, mux_sel=0, load=1
//             3'b100: out = 4'b1111; // ADD   alu_sel=11, mux_sel=1, load=1 (feedback ALU result)
//             3'b101: out = 4'b1111; // ADD   alu_sel=11, mux_sel=1, load=1
//             3'b110: out = 4'b1111; // ADD   alu_sel=11, mux_sel=1, load=1
//             default: out = 4'b0000; // Default: AND, mux_sel=0, load=0 (NOP)
//         endcase
//     end

// endmodule

module rom (
    input [2:0] addr,
    output reg [3:0] out
);

    always @(*) begin
        case (addr)
            // Test AND: should clear reg (possible zero)
            3'b000: out = 4'b0001; // alu_sel=00 (AND), mux_sel=0, load=1

            // Test XOR: reg_data ^ alu_in_data; use equal operands to get zero
            3'b001: out = 4'b1001; // alu_sel=10 (XOR), mux_sel=0, load=1

            // Test ADD: initial addition, no overflow
            3'b010: out = 4'b1101; // alu_sel=11 (ADD), mux_sel=0, load=1

            // Test ADD with feedback: reg + alu_in_data, accumulates value
            3'b011: out = 4'b1111; // alu_sel=11 (ADD), mux_sel=1, load=1

            // Another ADD with feedback to try overflow
            3'b100: out = 4'b1111; // alu_sel=11 (ADD), mux_sel=1, load=1

            // Test XOR again: clear reg if operands match (zero flag test)
            3'b101: out = 4'b1001; // alu_sel=10 (XOR), mux_sel=0, load=1

            // Test ADD again
            3'b110: out = 4'b1101; // alu_sel=11 (ADD), mux_sel=0, load=1

            default: out = 4'b0000; // Default: NOP (AND with load=0)
        endcase
    end

endmodule

cpu_controller/program_counter/program_counter.v
module program_counter(
    input clk, rstn,
    output reg [2:0] out
);
always @(posedge clk) begin
    if (!rstn)
        out <= 0;
    else
        out <= out + 1;
end

endmodule

//output
//0 - 000
//1 - 001
//2 - 010
//3 - 011
//4 - 100
//...

cpu_controller/cpu.v
module cpu (
    input [3:0] mux_in_data, alu_in_data,
    input clk, rstn,
    output carry_out,
    output [3:0] rom_out, alu_out, reg_out,
    output [2:0] pc_out
);

    wire [3:0] rom_instruction;
    wire [3:0] reg_data, alu_result, mux_out;
    wire [2:0] pc_addr;

    wire [1:0] alu_sel;
    wire mux_sel, load;

    // Program Counter
    program_counter pc_inst (
        .clk(clk),
        .rstn(rstn),
        .out(pc_addr)
    );

    // ROM providing control signals
    rom rom_inst (
        .addr(pc_addr),
        .out(rom_instruction)
    );

    assign alu_sel = rom_instruction[3:2];
    assign mux_sel = rom_instruction[1];
    assign load    = rom_instruction[0];

    // Datapath (Register + MUX + ALU)
    mux mux_inst (
        .a(mux_in_data),
        .b(alu_result),
        .sel(mux_sel),
        .out(mux_out)
    );

    register reg_inst (
        .clk(clk),
        .load(load),
        .rstn(rstn),
        .d(mux_out),
        .q(reg_data)
    );

    alu alu_inst (
        .a(reg_data),
        .b(alu_in_data),
        .sel(alu_sel),
        .out(alu_result),
        .carry_out(carry_out)
    );

    // Outputs for observation
    assign reg_out = reg_data;
    assign alu_out = alu_result;
    assign rom_out = rom_instruction;
    assign pc_out  = pc_addr;

endmodule

cpu_controller/testbench.v
// `timescale 1ns/1ps
// `default_nettype none

// module testbench;

//     reg clk, rstn;
//     reg [3:0] mux_in_data, alu_in_data;
//     wire carry_out;
//     wire [3:0] rom_out, alu_out, reg_out;
//     wire [2:0] pc_out;

//     reg [1023:0] vcdfile;

//     cpu uut(
//         .mux_in_data(mux_in_data),
//         .alu_in_data(alu_in_data),
//         .clk(clk),
//         .rstn(rstn),
//         .carry_out(carry_out),
//         .rom_out(rom_out),
//         .alu_out(alu_out),
//         .reg_out(reg_out),
//         .pc_out(pc_out)
//     );

//     localparam CLK_PERIOD = 10;

//     // Clock generation
//     initial begin
//         clk = 0;
//         forever #(CLK_PERIOD/2) clk = ~clk;
//     end

//     // VCD file generation
//     initial begin
//         if (!$value$plusargs("vcd=%s", vcdfile)) begin
//             vcdfile = "cpu_wave.vcd";
//         end
//         $dumpfile(vcdfile);
//         $dumpvars(0, testbench);
//     end

//     // Test sequence
//     initial begin
//         rstn = 0;
//         mux_in_data = 4'b0010;
//         alu_in_data = 4'b0001;
//         #10;  // Apply reset
//         rstn = 1; #5; // Release reset

//         // Instruction execution cycles
//         repeat (10) begin
//             #(CLK_PERIOD);
//             $display("PC: %0d | ROM: %b | Reg: %0d | ALU: %0d | Carry: %b", 
//                       pc_out, rom_out, reg_out, alu_out, carry_out);
//         end

//         $finish;
//     end

// endmodule
// `default_nettype wire


`timescale 1ns/1ps
`default_nettype none

module testbench;

    reg clk, rstn;
    reg [3:0] mux_in_data, alu_in_data;
    wire carry_out;
    wire [3:0] rom_out, alu_out, reg_out;
    wire [2:0] pc_out;

    reg [1023:0] vcdfile;

    cpu uut(
        .mux_in_data(mux_in_data),
        .alu_in_data(alu_in_data),
        .clk(clk),
        .rstn(rstn),
        .carry_out(carry_out),
        .rom_out(rom_out),
        .alu_out(alu_out),
        .reg_out(reg_out),
        .pc_out(pc_out)
    );

    localparam CLK_PERIOD = 10;

    // Clock generation
    initial begin
        clk = 0;
        forever #(CLK_PERIOD/2) clk = ~clk;
    end

    // VCD file generation
    initial begin
        if (!$value$plusargs("vcd=%s", vcdfile)) begin
            vcdfile = "cpu_wave.vcd";
        end
        $dumpfile(vcdfile);
        $dumpvars(0, testbench);
    end

    // Test sequence
    initial begin
        // Initial values
        rstn = 0;
        mux_in_data = 4'b0010;
        alu_in_data = 4'b0001;

        #10;        // Hold reset low
        rstn = 1;   // Release reset
        #5;

        $display("----- Starting CPU Test -----");

        // Initial instruction cycles
        repeat (5) begin
            #(CLK_PERIOD);
            $display("Time: %0t | PC: %0d | ROM: %b | Reg: %0d | ALU: %0d | Carry: %b", 
                     $time, pc_out, rom_out, reg_out, alu_out, carry_out);
        end

        // Change external inputs
        $display("----- Changing Inputs -----");
        mux_in_data = 4'b1111;
        alu_in_data = 4'b0011;

        // More instruction cycles after input change
        repeat (5) begin
            #(CLK_PERIOD);
            $display("Time: %0t | PC: %0d | ROM: %b | Reg: %0d | ALU: %0d | Carry: %b", 
                     $time, pc_out, rom_out, reg_out, alu_out, carry_out);
        end

        $display("----- Test Completed -----");

        $stop;    // Pause simulation (useful in interactive runs)
        $finish;  // End simulation
    end

endmodule

`default_nettype wire

cpu_controller/wave.vcd
$date
	Sun Jul 06 10:21:39 2025
$end
$version
	Icarus Verilog
$end
$timescale
	1ps
$end
$scope module testbench $end
$var wire 4 ! rom_out [3:0] $end
$var wire 4 " reg_out [3:0] $end
$var wire 3 # pc_out [2:0] $end
$var wire 1 $ carry_out $end
$var wire 4 % alu_out [3:0] $end
$var parameter 32 & CLK_PERIOD $end
$var reg 4 ' alu_in_data [3:0] $end
$var reg 1 ( clk $end
$var reg 4 ) mux_in_data [3:0] $end
$var reg 1 * rstn $end
$var reg 1024 + vcdfile [1023:0] $end
$scope module uut $end
$var wire 4 , alu_in_data [3:0] $end
$var wire 4 - alu_out [3:0] $end
$var wire 1 ( clk $end
$var wire 4 . mux_in_data [3:0] $end
$var wire 3 / pc_out [2:0] $end
$var wire 4 0 reg_out [3:0] $end
$var wire 4 1 rom_out [3:0] $end
$var wire 1 * rstn $end
$var wire 4 2 rom_instruction [3:0] $end
$var wire 4 3 reg_data [3:0] $end
$var wire 3 4 pc_addr [2:0] $end
$var wire 1 5 mux_sel $end
$var wire 4 6 mux_out [3:0] $end
$var wire 1 7 load $end
$var wire 1 $ carry_out $end
$var wire 2 8 alu_sel [1:0] $end
$var wire 4 9 alu_result [3:0] $end
$scope module alu_inst $end
$var wire 4 : b [3:0] $end
$var wire 2 ; sel [1:0] $end
$var wire 4 < a [3:0] $end
$var reg 1 $ carry_out $end
$var reg 4 = out [3:0] $end
$var reg 1 > zero_flag $end
$upscope $end
$scope module mux_inst $end
$var wire 4 ? a [3:0] $end
$var wire 4 @ b [3:0] $end
$var wire 1 5 sel $end
$var wire 4 A out [3:0] $end
$upscope $end
$scope module pc_inst $end
$var wire 1 ( clk $end
$var wire 1 * rstn $end
$var reg 3 B out [2:0] $end
$upscope $end
$scope module reg_inst $end
$var wire 1 ( clk $end
$var wire 4 C d [3:0] $end
$var wire 1 7 load $end
$var wire 1 * rstn $end
$var reg 4 D q [3:0] $end
$upscope $end
$scope module rom_inst $end
$var wire 3 E addr [2:0] $end
$var reg 4 F out [3:0] $end
$upscope $end
$upscope $end
$upscope $end
$enddefinitions $end
$comment Show the parameter values. $end
$dumpall
b1010 &
$end
#0
$dumpvars
b1 F
b0 E
b0 D
b10 C
b0 B
b10 A
b0 @
b10 ?
1>
b0 =
b0 <
b0 ;
b1 :
b0 9
b0 8
17
b10 6
05
b0 4
b0 3
b1 2
b1 1
b0 0
b0 /
b10 .
b0 -
b1 ,
b110001101110000011101010101111101100011011011110110111001110100011100100110111101101100011011000110010101110010001011110111011101100001011101100110010100101110011101100110001101100100 +
0*
b10 )
0(
b1 '
b0 %
0$
b0 #
b0 "
b1 !
$end
#5000
1(
#10000
0(
1*
#15000
0>
b11 %
b11 -
b11 9
b11 =
b11 @
b1 8
b1 ;
b101 !
b101 1
b101 2
b101 F
b1 #
b1 /
b1 4
b1 B
b1 E
b10 "
b10 0
b10 3
b10 <
b10 D
1(
#20000
0(
#25000
b10 8
b10 ;
b1001 !
b1001 1
b1001 2
b1001 F
b10 #
b10 /
b10 4
b10 B
b10 E
1(
#30000
0(
#35000
b11 8
b11 ;
b1101 !
b1101 1
b1101 2
b1101 F
b11 #
b11 /
b11 4
b11 B
b11 E
1(
#40000
0(
#45000
b11 6
b11 A
b11 C
15
b1111 !
b1111 1
b1111 2
b1111 F
b100 #
b100 /
b100 4
b100 B
b100 E
1(
#50000
0(
#55000
b100 6
b100 A
b100 C
b100 %
b100 -
b100 9
b100 =
b100 @
b101 #
b101 /
b101 4
b101 B
b101 E
b11 "
b11 0
b11 3
b11 <
b11 D
1(
#60000
0(
#65000
b100 "
b100 0
b100 3
b100 <
b100 D
b110 #
b110 /
b110 4
b110 B
b110 E
b111 6
b111 A
b111 C
b111 %
b111 -
b111 9
b111 =
b111 @
1(
b11 '
b11 ,
b11 :
b1111 )
b1111 .
b1111 ?
#70000
0(
#75000
07
05
b0 8
b0 ;
b1111 6
b1111 A
b1111 C
b0 !
b0 1
b0 2
b0 F
b11 %
b11 -
b11 9
b11 =
b11 @
b111 #
b111 /
b111 4
b111 B
b111 E
b111 "
b111 0
b111 3
b111 <
b111 D
1(
#80000
0(
#85000
17
b1 !
b1 1
b1 2
b1 F
b0 #
b0 /
b0 4
b0 B
b0 E
1(
#90000
0(
#95000
b1111 %
b1111 -
b1111 9
b1111 =
b1111 @
b1 8
b1 ;
b101 !
b101 1
b101 2
b101 F
b1 #
b1 /
b1 4
b1 B
b1 E
b1111 "
b1111 0
b1111 3
b1111 <
b1111 D
1(
#100000
0(
#105000
b1100 %
b1100 -
b1100 9
b1100 =
b1100 @
b10 8
b10 ;
b1001 !
b1001 1
b1001 2
b1001 F
b10 #
b10 /
b10 4
b10 B
b10 E
1(
#110000
0(
#115000
1$
b10 %
b10 -
b10 9
b10 =
b10 @
b11 8
b11 ;
b1101 !
b1101 1
b1101 2
b1101 F
b11 #
b11 /
b11 4
b11 B
b11 E
1(
